{
  "version": "7",
  "dialect": "postgresql",
  "entries": [
    {
      "idx": 0,
      "version": "7",
      "when": 1773824928196,
      "tag": "0000_warm_apocalypse",
      "breakpoints": true
    },
    {
      "idx": 1,
      "version": "7",
      "when": 1774206841317,
      "tag": "0001_luxuriant_gorgon",
      "breakpoints": true
    },
    {
      "idx": 2,
      "version": "7",
      "when": 1774210822789,
      "tag": "0002_nebulous_diamondback",
      "breakpoints": true
    },
    {
      "idx": 3,
      "version": "7",
      "when": 1774211136462,
      "tag": "0003_last_carnage",
      "breakpoints": true
    },
    {
      "idx": 4,
      "version": "7",
      "when": 1780488283146,
      "tag": "0004_dark_wendell_vaughn",
      "breakpoints": true
    },
    {
      "idx": 5,
      "version": "7",
      "when": 1781444469379,
      "tag": "0005_grey_winter_soldier",
      "breakpoints": true
    },
    {
      "idx": 6,
      "version": "7",
      "when": 1781948330155,
      "tag": "0006_closed_dust",
      "breakpoints": true
    }
  ]
}